{
 "awd_id": "0215734",
 "agcy_id": "NSF",
 "tran_type": "Grant",
 "awd_istr_txt": "Standard Grant",
 "awd_titl_txt": "MRI/RUI Proposal: Acquisition of an Inductively Coupled Plasma Atomic Emission Spectrometer and Microwave Digestion System",
 "cfda_num": "47.050",
 "org_code": "06030000",
 "po_phone": null,
 "po_email": "",
 "po_sign_block_name": "Russell Kelz",
 "awd_eff_date": "2002-08-15",
 "awd_exp_date": "2004-07-31",
 "tot_intn_awd_amt": 88764.0,
 "awd_amount": 88764.0,
 "awd_min_amd_letter_date": "2002-07-30",
 "awd_max_amd_letter_date": "2002-07-30",
 "awd_abstract_narration": "0215734\r\nSchaumloffel\r\n\r\nWith this award from the MRI program, the State University of New York College at Oneonta (SUNY Oneonta) will acquire an inductively coupled plasma atomic emission spectrometer (ICP-AES) and microwave digestion system (MDS). The research carried out with these instruments, both at SUNY Oneonta and with colleagues at nearby Hartwick College, involves a wide array of geological, environmental and chemical studies. These include studies of the elemental composition of metamorphic rock formations in New York and Montana, studies on the cycling of trace elements in environmental systems and specific studies of the accumulation and cycling of mercury in the Adirondack Region (New York). A major component of this project is the involvement of undergraduate students in laboratory-based research linked with field-work and the analysis of geological features in the field. The acquisition of this instrumentation will greatly enhance our suite of shared analytical instrumentation at SUNY Oneonta, benefiting the research of a number of faculty members and improving undergraduate education.\r\n***\r\n\r\n",
 "awd_arra_amount": 0.0,
 "dir_abbr": "GEO",
 "org_dir_long_name": "Directorate for Geosciences",
 "div_abbr": "EAR",
 "org_div_long_name": "Division Of Earth Sciences",
 "awd_agcy_code": "4900",
 "fund_agcy_code": "4900",
 "pi": [
  {
   "pi_role": "Principal Investigator",
   "pi_first_name": "John",
   "pi_last_name": "Schaumloffel",
   "pi_mid_init": "C",
   "pi_sufx_name": "",
   "pi_full_name": "John C Schaumloffel",
   "pi_email_addr": "jschauml@fitchburgstate.edu",
   "nsf_id": "000147650",
   "pi_start_date": "2002-07-30",
   "pi_end_date": null
  }
 ],
 "inst": {
  "inst_name": "SUNY College at Oneonta",
  "inst_street_address": "108 RAVINE PKWY",
  "inst_street_address_2": "",
  "inst_city_name": "ONEONTA",
  "inst_state_code": "NY",
  "inst_state_name": "New York",
  "inst_phone_num": "6074362525",
  "inst_zip_code": "138202685",
  "inst_country_name": "United States",
  "cong_dist_code": "19",
  "st_cong_dist_code": "NY19",
  "org_lgl_bus_name": "RESEARCH FOUNDATION FOR THE STATE UNIVERSITY OF NEW YORK, THE",
  "org_prnt_uei_num": "GMZUKXFDJMA9",
  "org_uei_num": "KBTNGWV8WML7"
 },
 "perf_inst": {
  "perf_inst_name": "SUNY College at Oneonta",
  "perf_str_addr": "108 RAVINE PKWY",
  "perf_city_name": "ONEONTA",
  "perf_st_code": "NY",
  "perf_st_name": "New York",
  "perf_zip_code": "138202685",
  "perf_ctry_code": "US",
  "perf_cong_dist": "19",
  "perf_st_cong_dist": "NY19",
  "perf_ctry_name": "",
  "perf_ctry_flag": "1"
 },
 "pgm_ele": [
  {
   "pgm_ele_code": "118900",
   "pgm_ele_name": "Major Research Instrumentation"
  }
 ],
 "pgm_ref": [
  {
   "pgm_ref_code": "0000",
   "pgm_ref_txt": "UNASSIGNED"
  },
  {
   "pgm_ref_code": "1189",
   "pgm_ref_txt": "MAJOR RESEARCH INSTRUMENTATION"
  },
  {
   "pgm_ref_code": "9141",
   "pgm_ref_txt": "RES IN UNDERGRAD. INST - EQUIP"
  },
  {
   "pgm_ref_code": "9178",
   "pgm_ref_txt": "UNDERGRADUATE EDUCATION"
  },
  {
   "pgm_ref_code": "9229",
   "pgm_ref_txt": "RES IN UNDERGRAD INST-RESEARCH"
  },
  {
   "pgm_ref_code": "OTHR",
   "pgm_ref_txt": "OTHER RESEARCH OR EDUCATION"
  }
 ],
 "app_fund": [
  {
   "app_code": "0102",
   "app_name": "NSF RESEARCH & RELATED ACTIVIT",
   "app_symb_id": "490100",
   "fund_code": "app-0102",
   "fund_name": "",
   "fund_symb_id": ""
  }
 ],
 "oblg_fy": [
  {
   "fund_oblg_fiscal_yr": 2002,
   "fund_oblg_amt": 88764.0
  }
 ],
 "por": null
}